masto/__init__.py
masto/masto.py
masto-2.0.6.dist-info/LICENSE
masto-2.0.6.dist-info/METADATA
masto-2.0.6.dist-info/WHEEL
masto-2.0.6.dist-info/entry_points.txt
masto-2.0.6.dist-info/top_level.txt
masto-2.0.6.dist-info/RECORD
