Metadata-Version: 2.2
Name: masto
Version: 2.0.6
Summary: Masto OSINT Tool Python package for Mastodon user investigations.
Home-page: https://github.com/C3n7ral051nt4g3ncy/Masto
Author: OSINT_Tactical (AKA C3n7ral051nt4g3ncy)
Author-email: C3n7ral051nt4g3ncy@tactical-osint-academy.com
Classifier: Programming Language :: Python :: 3
Classifier: License :: OSI Approved :: MIT License
Classifier: Operating System :: OS Independent
Requires-Python: >=3.6
License-File: LICENSE
Requires-Dist: bs4
Requires-Dist: tqdm
Requires-Dist: urllib3
Requires-Dist: argparse
Requires-Dist: w3lib
Requires-Dist: aiohttp
Requires-Dist: asyncio
Requires-Dist: requests
Dynamic: author
Dynamic: author-email
Dynamic: classifier
Dynamic: description
Dynamic: description-content-type
Dynamic: home-page
Dynamic: requires-dist
Dynamic: requires-python
Dynamic: summary
